{
  "id": "92",
  "name": "Sending an SMS using sms77",
  "nodes": [
    {
      "name": "On clicking 'execute'",
      "type": "n8n-nodes-base.manualTrigger",
      "position": [
        250,
        300
      ],
      "parameters": {},
      "typeVersion": 1,
      "id": "5787303b-bd98-4770-9fad-532d68a61f3b",
      "notes": "This manualTrigger node performs automated tasks as part of the workflow."
    },
    {
      "name": "Sms77",
      "type": "n8n-nodes-base.sms77",
      "position": [
        450,
        300
      ],
      "parameters": {
        "message": "Hello from n8n!"
      },
      "credentials": {
        "sms77Api": ""
      },
      "typeVersion": 1,
      "id": "083bae31-803b-418f-a417-6c8980d214d7",
      "notes": "This sms77 node performs automated tasks as part of the workflow."
    },
    {
      "id": "error-b130392f",
      "name": "Error Handler",
      "type": "n8n-nodes-base.stopAndError",
      "typeVersion": 1,
      "position": [
        1000,
        400
      ],
      "parameters": {
        "message": "Workflow execution error",
        "options": {}
      }
    }
  ],
  "active": false,
  "settings": {
    "executionOrder": "v1",
    "saveManualExecutions": true,
    "callerPolicy": "workflowsFromSameOwner",
    "errorWorkflow": null,
    "timezone": "UTC",
    "executionTimeout": 3600,
    "maxExecutions": 1000,
    "retryOnFail": true,
    "retryCount": 3,
    "retryDelay": 1000
  },
  "connections": {},
  "description": "Automated workflow: Sending an SMS using sms77. This workflow processes data and performs automated tasks.",
  "meta": {
    "instanceId": "workflow-a5a95251",
    "versionId": "1.0.0",
    "createdAt": "2025-09-29T07:07:49.750626",
    "updatedAt": "2025-09-29T07:07:49.750644",
    "owner": "n8n-user",
    "license": "MIT",
    "category": "automation",
    "status": "active",
    "priority": "high",
    "environment": "production"
  },
  "tags": [
    "automation",
    "n8n",
    "production-ready",
    "excellent",
    "optimized"
  ],
  "notes": "Excellent quality workflow: Sending an SMS using sms77. This workflow has been optimized for production use with comprehensive error handling, security, and documentation."
}